flowrules/__init__.py
flowrules/__version__.py
flowrules/rules_engine.py
py_flow_rules-0.1.0.dist-info/licenses/LICENSE
py_flow_rules-0.1.0.dist-info/METADATA
py_flow_rules-0.1.0.dist-info/WHEEL
py_flow_rules-0.1.0.dist-info/top_level.txt
py_flow_rules-0.1.0.dist-info/RECORD
