Metadata-Version: 2.4
Name: py-flow-rules
Version: 0.1.0
Summary: A simple rules engine package for python
Home-page: https://github.com/p1971/pyFlowRules
Author: Pete Robinson
Author-email: Pete Robinson <pete@madhippy.com>
License-Expression: MIT
Classifier: Development Status :: 4 - Beta
Classifier: Intended Audience :: Developers
Classifier: Operating System :: OS Independent
Classifier: Programming Language :: Python :: 3
Classifier: Programming Language :: Python :: 3.10
Classifier: Programming Language :: Python :: 3.11
Classifier: Programming Language :: Python :: 3.12
Classifier: Programming Language :: Python :: 3.13
Classifier: Topic :: Software Development :: Libraries :: Python Modules
Classifier: Topic :: Software Development :: Libraries :: Application Frameworks
Requires-Python: >=3.10
License-File: LICENSE
Dynamic: license-file
